woollylib/__init__.py
woollylib/dataset.py
woollylib/main.py
woollylib/scheduler.py
woollylib/training.py
woollylib-0.0.5.dist-info/LICENSE
woollylib-0.0.5.dist-info/METADATA
woollylib-0.0.5.dist-info/WHEEL
woollylib-0.0.5.dist-info/top_level.txt
woollylib-0.0.5.dist-info/RECORD
